kintree/__init__.py
kintree/common/part_tools.py
kintree/common/progress.py
kintree/common/tools.py
kintree/config/automationdirect/automationdirect_api.yaml
kintree/config/automationdirect/automationdirect_config.yaml
kintree/config/config_interface.py
kintree/config/digikey/digikey_api.yaml
kintree/config/digikey/digikey_categories.yaml
kintree/config/digikey/digikey_config.yaml
kintree/config/element14/element14_api.yaml
kintree/config/element14/element14_config.yaml
kintree/config/inventree/categories.yaml
kintree/config/inventree/inventree_dev.yaml
kintree/config/inventree/inventree_prod.yaml
kintree/config/inventree/parameters.yaml
kintree/config/inventree/parameters_filters.yaml
kintree/config/inventree/stock_locations.yaml
kintree/config/inventree/supplier_parameters.yaml
kintree/config/inventree/suppliers.yaml
kintree/config/jameco/jameco_api.yaml
kintree/config/jameco/jameco_config.yaml
kintree/config/kicad/kicad.yaml
kintree/config/kicad/kicad_map.yaml
kintree/config/lcsc/lcsc_api.yaml
kintree/config/lcsc/lcsc_config.yaml
kintree/config/mouser/mouser_api.yaml
kintree/config/mouser/mouser_config.yaml
kintree/config/settings.py
kintree/config/tme/tme_api.yaml
kintree/config/tme/tme_config.yaml
kintree/config/user/general.yaml
kintree/config/user/internal_part_number.yaml
kintree/config/user/search_api.yaml
kintree/database/inventree_api.py
kintree/database/inventree_interface.py
kintree/gui/gui.py
kintree/gui/logo.ico
kintree/gui/views/common.py
kintree/gui/views/main.py
kintree/gui/views/settings.py
kintree/kicad/kicad_interface.py
kintree/kicad/kicad_symbol.py
kintree/kicad/templates/LICENSE
kintree/kicad/templates/capacitor-polarized.kicad_sym
kintree/kicad/templates/capacitor.kicad_sym
kintree/kicad/templates/connector.kicad_sym
kintree/kicad/templates/crystal-2p.kicad_sym
kintree/kicad/templates/default.kicad_sym
kintree/kicad/templates/diode-led.kicad_sym
kintree/kicad/templates/diode-schottky.kicad_sym
kintree-1.1.4.dist-info/LICENSE
kintree-1.1.4.dist-info/METADATA
kintree-1.1.4.dist-info/WHEEL
kintree-1.1.4.dist-info/entry_points.txt
kintree-1.1.4.dist-info/RECORD
