Metadata-Version: 2.1
Name: kintree
Version: 1.1.4
Summary: Fast part creation in KiCad and InvenTree
Home-page: https://github.com/sparkmicro/Ki-nTree
License: GPL-3.0-or-later
Keywords: inventree,kicad,digikey,mouser,component,part,create
Author: eeintech
Author-email: eeintech@eeinte.ch
Maintainer: eeintech
Maintainer-email: eeintech@eeinte.ch
Requires-Python: >=3.9,<3.12
Classifier: License :: OSI Approved :: GNU General Public License v3 or later (GPLv3+)
Classifier: Programming Language :: Python :: 3
Classifier: Programming Language :: Python :: 3.9
Classifier: Programming Language :: Python :: 3.10
Classifier: Programming Language :: Python :: 3.11
Requires-Dist: cloudscraper (>=1.2.71,<2.0.0)
Requires-Dist: digikey-api (>=1.0.0,<2.0.0)
Requires-Dist: flet (>=0.24.1,<0.25.0)
Requires-Dist: inventree (>=0.17.0,<0.18.0)
Requires-Dist: kiutils (>=1.4.0,<2.0.0)
Requires-Dist: mouser (>=0.1.3,<0.2.0)
Requires-Dist: multiprocess (>=0.70.12,<0.71.0)
Requires-Dist: pyyaml (>=6.0.1,<7.0.0)
Requires-Dist: thefuzz (>=0.19.0,<0.20.0)
Requires-Dist: validators (>=0.19.0,<0.20.0)
Requires-Dist: wrapt_timeout_decorator (>=1.3.12,<2.0.0)
Project-URL: Repository, https://github.com/sparkmicro/Ki-nTree
